customlatexalexutk/__init__.py
customlatexalexutk/utils.py
customlatexalexutk-0.1.0.dist-info/METADATA
customlatexalexutk-0.1.0.dist-info/WHEEL
customlatexalexutk-0.1.0.dist-info/RECORD
