Metadata-Version: 2.1
Name: customlatexalexutk
Version: 0.1.0
Summary: My homework
Author: alex-utk
Author-email: alex.com195@gmail.com
Requires-Python: >=3.10,<4.0
Classifier: Programming Language :: Python :: 3
Classifier: Programming Language :: Python :: 3.10
Classifier: Programming Language :: Python :: 3.11
Classifier: Programming Language :: Python :: 3.12
